pystrap/__init__.py
pystrap-0.0.1.dist-info/top_level.txt
pystrap-0.0.1.dist-info/METADATA
pystrap-0.0.1.dist-info/DESCRIPTION.rst
pystrap-0.0.1.dist-info/metadata.json
pystrap-0.0.1.dist-info/WHEEL
pystrap-0.0.1.dist-info/RECORD
