Metadata-Version: 2.0
Name: pystrap
Version: 0.0.1
Summary: Interactively create a new Python skeleton project ready for PyPI deployment!
Home-page: https://github.com/themattrix/python-pystrap
Author: Matthew Tardiff
Author-email: mattrix@gmail.com
License: MIT
Platform: UNKNOWN
Classifier: License :: OSI Approved :: MIT License
Classifier: Programming Language :: Python :: 2
Classifier: Programming Language :: Python :: 2.6
Classifier: Programming Language :: Python :: 2.7
Classifier: Programming Language :: Python :: 3
Classifier: Programming Language :: Python :: 3.2
Classifier: Programming Language :: Python :: 3.3
Classifier: Programming Language :: Python :: 3.4
Classifier: Programming Language :: Python :: Implementation :: CPython
Classifier: Programming Language :: Python :: Implementation :: PyPy
